fabric_mb/__init__.py
fabric_mb/message_bus/__init__.py
fabric_mb/message_bus/abc_mb_api.py
fabric_mb/message_bus/admin.py
fabric_mb/message_bus/consumer.py
fabric_mb/message_bus/message_bus_exception.py
fabric_mb/message_bus/producer.py
fabric_mb/message_bus/messages/__init__.py
fabric_mb/message_bus/messages/abc_message_avro.py
fabric_mb/message_bus/messages/abc_object_avro.py
fabric_mb/message_bus/messages/actor_avro.py
fabric_mb/message_bus/messages/add_peer_avro.py
fabric_mb/message_bus/messages/add_reservation_avro.py
fabric_mb/message_bus/messages/add_reservations_avro.py
fabric_mb/message_bus/messages/add_slice_avro.py
fabric_mb/message_bus/messages/add_update_reservation_record.py
fabric_mb/message_bus/messages/add_update_slice_record.py
fabric_mb/message_bus/messages/auth_avro.py
fabric_mb/message_bus/messages/broker_query_model_avro.py
fabric_mb/message_bus/messages/claim_delegation_avro.py
fabric_mb/message_bus/messages/claim_resources_avro.py
fabric_mb/message_bus/messages/close_avro.py
fabric_mb/message_bus/messages/close_delegations_avro.py
fabric_mb/message_bus/messages/close_reservations_avro.py
fabric_mb/message_bus/messages/constants.py
fabric_mb/message_bus/messages/delegation_avro.py
fabric_mb/message_bus/messages/demand_reservation_avro.py
fabric_mb/message_bus/messages/extend_lease_avro.py
fabric_mb/message_bus/messages/extend_reservation_avro.py
fabric_mb/message_bus/messages/extend_ticket_avro.py
fabric_mb/message_bus/messages/failed_rpc_avro.py
fabric_mb/message_bus/messages/get_actors_request_avro.py
fabric_mb/message_bus/messages/get_broker_query_model_request_avro.py
fabric_mb/message_bus/messages/get_delegations_avro.py
fabric_mb/message_bus/messages/get_reservation_units_request_avro.py
fabric_mb/message_bus/messages/get_reservations_request_avro.py
fabric_mb/message_bus/messages/get_reservations_state_request_avro.py
fabric_mb/message_bus/messages/get_sites_request_avro.py
fabric_mb/message_bus/messages/get_slices_request_avro.py
fabric_message_bus-1.9.0.dist-info/LICENSE
fabric_message_bus-1.9.0.dist-info/WHEEL
fabric_message_bus-1.9.0.dist-info/METADATA
fabric_message_bus-1.9.0.dist-info/RECORD
