Metadata-Version: 2.1
Name: fabric_message_bus
Version: 1.9.0
Summary: Fabric Message Bus Schema
Keywords: Kafka,Fabric Message Bus Schema,Avro
Author-email: Komal Thareja <kthare10@renci.org>
Requires-Python: >=3.9
Classifier: Programming Language :: Python :: 3
Classifier: License :: OSI Approved :: MIT License
Classifier: Operating System :: OS Independent
Requires-Dist: confluent-kafka[avro]
Project-URL: Home, https://fabric-testbed.net/
Project-URL: Sources, https://github.com/fabric-testbed/MessageBusSchema
